{"httpProtocol":"HTTP/1.1","clientAcceptEncoding":"gzip, deflate, br","requestPriority":"","edgeRequestKeepAliveStatus":1,"requestHeaderNames":{},"clientTcpRtt":12,"clientQuicRtt":0,"colo":"EWR","asn":701,"asOrganization":"Verizon Business","country":"US","isEUCountry":false,"city":"Greenwich","continent":"NA","region":"Connecticut","regionCode":"CT","timezone":"America/New_York","longitude":"-73.62846","latitude":"41.02649","postalCode":"06836","metroCode":"501","tlsVersion":"TLSv1.3","tlsCipher":"AEAD-AES256-GCM-SHA384","tlsClientRandom":"0EuDAXuyBRsz8ccjYW/uWbjdQZWkcSwxmiH+uQJYfPg=","tlsClientCiphersSha1":"kXrN3VEKDdzz2cPKTQaKzpxVTxQ=","tlsClientExtensionsSha1":"1eY97BUYYO8vDaTfHQywB1pcNdM=","tlsClientExtensionsSha1Le":"u4wtEMFQBY18l3BzHAvORm+KGRw=","tlsExportedAuthenticator":{"clientHandshake":"9bc8ca1fdd992b6183dd9371ca17b4d617f4a71088ffce8bd5593ef84b46f42c0b7af3ad0b28a22ba43c4366c3ef8ee2","serverHandshake":"14e9af427c1156efa173b3e5049144594816c1784edf54892e8191342e04ffaa60493bc72a8e69bedf2355246a74e21c","clientFinished":"3a4e85a5f0d205bfafca77ca2fe8b277e79679992e2f21d75b4ef9d833b3b9b688b797a92f38dfe547b9f63558a4e12c","serverFinished":"7e58a2fc6c8bdcfeb7f124044ce4f5e1617d6d1d12913be8c23c5b689351ecebf55eca75e36cb543915f039d0dacd61a"},"tlsClientHelloLength":"1603","tlsClientAuth":{"certPresented":"0","certVerified":"NONE","certRevoked":"0","certIssuerDN":"","certSubjectDN":"","certIssuerDNRFC2253":"","certSubjectDNRFC2253":"","certIssuerDNLegacy":"","certSubjectDNLegacy":"","certSerial":"","certIssuerSerial":"","certSKI":"","certIssuerSKI":"","certFingerprintSHA1":"","certFingerprintSHA256":"","certNotBefore":"","certNotAfter":"","certRFC9440":"","certRFC9440TooLarge":false,"certChainRFC9440":"","certChainRFC9440TooLarge":false},"verifiedBotCategory":"","edgeL4":{"deliveryRate":236768},"botManagement":{"corporateProxy":false,"verifiedBot":false,"jsDetection":{"passed":false},"staticResource":false,"detectionIds":{},"score":99}}